wyrd/__init__.py
wyrd/py.typed
wyrd/version.py
wyrd/constrained_types/__init__.py
wyrd/constrained_types/core.py
wyrd/constrained_types/helpers.py
wyrd/constrained_types/primitives.py
wyrd/read_once/__init__.py
wyrd/read_once/core.py
wyrd-0.8.1.dist-info/LICENSE
wyrd-0.8.1.dist-info/WHEEL
wyrd-0.8.1.dist-info/METADATA
wyrd-0.8.1.dist-info/RECORD
