Metadata-Version: 2.1
Name: wyrd
Version: 0.8.1
Summary: Library for helpers with Domain driven security
Home-page: https://github.com/meadsteve/constrained_types/
Author: meadsteve
Author-email: meadsteve@gmail.com
Requires-Python: ~=3.6
Classifier: License :: OSI Approved :: MIT License
